LICENSE
MANIFEST.in
README
setup.cfg
setup.py
concoord/__init__.py
concoord/asyncclientproxy.py
concoord/batchclientproxy.py
concoord/blockingclientproxy.py
concoord/clientproxy.py
concoord/codegen.py
concoord/connection.py
concoord/enums.py
concoord/exception.py
concoord/logdaemon.py
concoord/main.py
concoord/message.py
concoord/nameserver.py
concoord/node.py
concoord/pack.py
concoord/proxygenerator.py
concoord/pvalue.py
concoord/replica.py
concoord/responsecollector.py
concoord/route53.py
concoord/safetychecker.py
concoord/utils.py
concoord.egg-info/PKG-INFO
concoord.egg-info/SOURCES.txt
concoord.egg-info/dependency_links.txt
concoord.egg-info/entry_points.txt
concoord.egg-info/requires.txt
concoord.egg-info/top_level.txt
concoord/object/__init__.py
concoord/object/bank.py
concoord/object/barrier.py
concoord/object/binarytree.py
concoord/object/boundedsemaphore.py
concoord/object/condition.py
concoord/object/counter.py
concoord/object/jobmanager.py
concoord/object/lock.py
concoord/object/log.py
concoord/object/membership.py
concoord/object/meshmembership.py
concoord/object/nameservercoord.py
concoord/object/pinger.py
concoord/object/queue.py
concoord/object/rlock.py
concoord/object/semaphore.py
concoord/object/stack.py
concoord/openreplica/__init__.py
concoord/openreplica/main.py
concoord/openreplica/nodemanager.py
concoord/openreplica/openreplicanameserver.py
concoord/proxy/__init__.py
concoord/proxy/bank.py
concoord/proxy/barrier.py
concoord/proxy/binarytree.py
concoord/proxy/boundedsemaphore.py
concoord/proxy/condition.py
concoord/proxy/counter.py
concoord/proxy/jobmanager.py
concoord/proxy/lock.py
concoord/proxy/log.py
concoord/proxy/membership.py
concoord/proxy/meshmembership.py
concoord/proxy/nameservercoord.py
concoord/proxy/queue.py
concoord/proxy/rlock.py
concoord/proxy/semaphore.py
concoord/proxy/stack.py
concoord/proxy/test.py
concoord/test/__init__.py
concoord/test/test_partition.py
concoord/test/test_replicacomeback.py
concoord/test/test_replicacrashfailure.py
concoord/test/test_timeout.py
concoord/threadingobject/__init__.py
concoord/threadingobject/dboundedsemaphore.py
concoord/threadingobject/dcondition.py
