Metadata-Version: 1.0
Name: concoord
Version: 1.1.0
Summary: Coordination service for distributed systems.
Home-page: http://openreplica.org/
Author: Deniz Altinbuken, Emin Gun Sirer
Author-email: deniz@systems.cs.cornell.edu, egs@systems.cs.cornell.edu
License: 3-Clause BSD
Platform: UNKNOWN
Classifier: Development Status :: 3 - Alpha
Classifier: Intended Audience :: Developers
Classifier: Intended Audience :: System Administrators
Classifier: License :: OSI Approved :: BSD License
Classifier: Operating System :: MacOS :: MacOS X
Classifier: Operating System :: POSIX :: Linux
Classifier: Operating System :: Unix
Classifier: Programming Language :: Python
Classifier: Programming Language :: Python :: 2.7
